whoscraped/__init__.py
whoscraped/exceptions.py
whoscraped/functions.py
whoscraped-0.2.0.dist-info/METADATA
whoscraped-0.2.0.dist-info/WHEEL
whoscraped-0.2.0.dist-info/top_level.txt
whoscraped-0.2.0.dist-info/RECORD
