Metadata-Version: 2.1
Name: whoscraped
Version: 0.2.0
Summary: Scrape football data from WhoScored
Home-page: https://www.github.com/valensantarone/whoscraped
Author: Valko
Author-email: valensantarone@gmail.com
Classifier: Programming Language :: Python :: 3
Classifier: License :: OSI Approved :: MIT License
Classifier: Operating System :: OS Independent
Requires-Python: >=3.6
Requires-Dist: selenium
Requires-Dist: beautifulsoup4
Requires-Dist: pandas
